LICENSE
simple_status_client/SimpleStatusClient.py
simple_status_client/__init__.py
simple_status_client/models.py
simple_status_client-0.1.3.dist-info/LICENSE
simple_status_client-0.1.3.dist-info/WHEEL
simple_status_client-0.1.3.dist-info/METADATA
simple_status_client-0.1.3.dist-info/RECORD
