Metadata-Version: 2.1
Name: simple-status-client
Version: 0.1.3
Summary: A package for interacting with the Simple Status Server
Home-page: https://github.com/bravosierra99/SimpleStatusClient
License: GPL-3.0-or-later
Author: Benjamin Smith
Author-email: bravosierra99@gmail.com
Requires-Python: >=3.6.2,<4.0.0
Classifier: License :: OSI Approved :: GNU General Public License v3 or later (GPLv3+)
Classifier: Programming Language :: Python :: 3
Classifier: Programming Language :: Python :: 3.10
Classifier: Programming Language :: Python :: 3.7
Classifier: Programming Language :: Python :: 3.8
Classifier: Programming Language :: Python :: 3.9
Requires-Dist: fastapi (>=0.68.1,<0.69.0)
Requires-Dist: requests (>=2.26.0,<3.0.0)
Requires-Dist: yarl (>=1.6.3,<2.0.0)
Project-URL: Repository, https://github.com/bravosierra99/SimpleStatusClient
